wayback_downloader/__init__.py
wayback_downloader/downloader.py
wayback_downloader-0.1.6.dist-info/LICENSE
wayback_downloader-0.1.6.dist-info/METADATA
wayback_downloader-0.1.6.dist-info/WHEEL
wayback_downloader-0.1.6.dist-info/entry_points.txt
wayback_downloader-0.1.6.dist-info/RECORD
