Metadata-Version: 2.1
Name: wayback_downloader
Version: 0.1.6
Summary: A powerful CLI tool to download and archive historical versions of websites from the Wayback Machine.
Home-page: https://github.com/carygeo/wayback_downloader
License: MIT
Keywords: wayback,archive,downloader,web,history,internet archive
Author: Cary Greenwood
Author-email: carygreenwood@gmail.com
Requires-Python: >=3.7,<4.0
Classifier: Intended Audience :: Developers
Classifier: Intended Audience :: Information Technology
Classifier: License :: OSI Approved :: MIT License
Classifier: Programming Language :: Python
Classifier: Programming Language :: Python :: 3
Classifier: Programming Language :: Python :: 3.7
Classifier: Programming Language :: Python :: 3.8
Classifier: Programming Language :: Python :: 3.9
Classifier: Programming Language :: Python :: 3.10
Classifier: Programming Language :: Python :: 3.11
Classifier: Programming Language :: Python :: 3.12
Classifier: Topic :: Internet :: WWW/HTTP :: Indexing/Search
Classifier: Topic :: System :: Archiving
Requires-Dist: beautifulsoup4
Requires-Dist: requests
Requires-Dist: urllib3
Requires-Dist: wayback
Project-URL: Repository, https://github.com/carygeo/wayback_downloader
